deeqnlpy/__init__.py
deeqnlpy/_custom_dict.py
deeqnlpy/_custom_dict_client.py
deeqnlpy/_lang_service_client.py
deeqnlpy/_tagger.py
deeqnlpy/lib/baikal/__init__.py
deeqnlpy/lib/baikal/language/__init__.py
deeqnlpy/lib/baikal/language/custom_dict_pb2.py
deeqnlpy/lib/baikal/language/custom_dict_pb2_grpc.py
deeqnlpy/lib/baikal/language/dict_common_pb2.py
deeqnlpy/lib/baikal/language/dict_common_pb2_grpc.py
deeqnlpy/lib/baikal/language/language_service_pb2.py
deeqnlpy/lib/baikal/language/language_service_pb2_grpc.py
deeqnlpy/lib/google/api/__init__.py
deeqnlpy/lib/google/api/annotations_pb2.py
deeqnlpy/lib/google/api/http_pb2.py
deeqnlpy-0.9.4.dist-info/LICENSE
deeqnlpy-0.9.4.dist-info/WHEEL
deeqnlpy-0.9.4.dist-info/METADATA
deeqnlpy-0.9.4.dist-info/RECORD
